domapi/__init__.py
domapi/webapi_classes/__init__.py
domapi/webapi_classes/attrs.py
domapi/webapi_classes/elements.py
domapi/webapi_classes/xpath.py
py_domapi-1.0.0.dist-info/LICENSE
py_domapi-1.0.0.dist-info/METADATA
py_domapi-1.0.0.dist-info/WHEEL
py_domapi-1.0.0.dist-info/top_level.txt
py_domapi-1.0.0.dist-info/RECORD
