Metadata-Version: 2.1
Name: py-domapi
Version: 1.0.0
Summary: Modify and access an HTML document with a JavaScript-like API
Author-email: Carl Furtado <carlzfurtado@gmail.com>
License: BSD 3-Clause License
Project-URL: Homepage, https://github.com/User0332/domapi
Keywords: javascript,dom,document,document object model,html
Classifier: License :: OSI Approved :: BSD License
Classifier: Intended Audience :: Developers
Classifier: Programming Language :: Python
Classifier: Programming Language :: Python :: 3
Classifier: Topic :: Text Processing :: Markup :: HTML
Classifier: Operating System :: OS Independent
Requires-Python: >=3.9
License-File: LICENSE
Requires-Dist: lxml (>=4.9.0)
Requires-Dist: cssselect (>=1.2.0)
Requires-Dist: htmlmin (>=0.1.12)
